{
    "id": 8,
    "title": "SU-CONSUME 1",
    "componentType": {
        "name": "SU-CONSUME",
        "version": "3-2-1",
        "cat": "SU",
        "subCat": "CONSUME",
        "icon": "star"
    },
    "state": "UNDEPLOYED",
    "name": "su-consume-1",
    "description": "description of the su-consume 1",
    "jbi_part": "*** Configuration of a Service Unit to consume a service, JBI part ***",
    "jbi_part": {
        "wsdl": "",
        "interface_name": "Interface Name Example",
        "service_name": "https://localhost:8088/mockIntegrationServiceSOAP",
        "endpoint_name": true
    },
    "cdk_part": "*** Configuration of a Service Unit to consume a service, CDK part ***",
    "cdk_part": {
        "mep": "",
        "operation": "",
        "timeout": "30000"
    },
    "soap_part": "*** Configuration of a Service Unit to consume a service, SOAP part ***",
    "soap_part": {
        "soap_action": "",
        "enable_http_transport": true,
        "enable_https_transport": false,
        "enable_jms_transport": false
    }
}
